MANIFEST.in
README.md
pyproject.toml
setup.py
cffi_modules/dilithium2_clean.py
cffi_modules/dilithium3_clean.py
cffi_modules/dilithium5_clean.py
cffi_modules/mceliece348864_clean.py
cffi_modules/mceliece348864f_clean.py
cffi_modules/mceliece460896_clean.py
cffi_modules/mceliece460896f_clean.py
cffi_modules/mceliece6688128_clean.py
cffi_modules/mceliece6688128f_clean.py
cffi_modules/mceliece6960119_clean.py
cffi_modules/mceliece6960119f_clean.py
cffi_modules/mceliece8192128_clean.py
cffi_modules/mceliece8192128f_clean.py
cffi_modules/sphincs-sha2-128f-simple_clean.py
cffi_modules/sphincs-sha2-128s-simple_clean.py
cffi_modules/sphincs-sha2-192f-simple_clean.py
cffi_modules/sphincs-sha2-192s-simple_clean.py
cffi_modules/sphincs-sha2-256f-simple_clean.py
cffi_modules/sphincs-sha2-256s-simple_clean.py
cffi_modules/sphincs-shake-128f-simple_clean.py
cffi_modules/sphincs-shake-128s-simple_clean.py
cffi_modules/sphincs-shake-192f-simple_clean.py
cffi_modules/sphincs-shake-192s-simple_clean.py
cffi_modules/sphincs-shake-256f-simple_clean.py
cffi_modules/sphincs-shake-256s-simple_clean.py
lib/PQClean/crypto_kem/mceliece348864/clean/benes.c
lib/PQClean/crypto_kem/mceliece348864/clean/bm.c
lib/PQClean/crypto_kem/mceliece348864/clean/controlbits.c
lib/PQClean/crypto_kem/mceliece348864/clean/crypto_int16.c
lib/PQClean/crypto_kem/mceliece348864/clean/crypto_int32.c
lib/PQClean/crypto_kem/mceliece348864/clean/crypto_uint16.c
lib/PQClean/crypto_kem/mceliece348864/clean/crypto_uint32.c
lib/PQClean/crypto_kem/mceliece348864/clean/crypto_uint64.c
lib/PQClean/crypto_kem/mceliece348864/clean/decrypt.c
lib/PQClean/crypto_kem/mceliece348864/clean/encrypt.c
lib/PQClean/crypto_kem/mceliece348864/clean/gf.c
lib/PQClean/crypto_kem/mceliece348864/clean/operations.c
lib/PQClean/crypto_kem/mceliece348864/clean/pk_gen.c
lib/PQClean/crypto_kem/mceliece348864/clean/root.c
lib/PQClean/crypto_kem/mceliece348864/clean/sk_gen.c
lib/PQClean/crypto_kem/mceliece348864/clean/synd.c
src/pypqc_cffi_bindings_libre.egg-info/PKG-INFO
src/pypqc_cffi_bindings_libre.egg-info/SOURCES.txt
src/pypqc_cffi_bindings_libre.egg-info/dependency_links.txt
src/pypqc_cffi_bindings_libre.egg-info/requires.txt
src/pypqc_cffi_bindings_libre.egg-info/top_level.txt