Metadata-Version: 2.1
Name: pypqc-cffi-bindings-libre
Version: 0.0.1.dev0
License: MIT License
Classifier: License :: OSI Approved :: MIT License
Classifier: License :: Public Domain
Requires-Dist: cffi>=1.0.0; platform_python_implementation != "PyPy"
